classy_classification/__init__.py
classy_classification/classifiers/__init__.py
classy_classification/classifiers/classy_skeleton.py
classy_classification/classifiers/classy_spacy.py
classy_classification/classifiers/classy_standalone.py
classy_classification/examples/__init__.py
classy_classification/examples/data.py
classy_classification/examples/individual_transformer.py
classy_classification/examples/spacy_few_shot_external.py
classy_classification/examples/spacy_internal_embeddings.py
classy_classification/examples/spacy_zero_shot_external.py
classy_classification-1.0.2.dist-info/LICENSE
classy_classification-1.0.2.dist-info/METADATA
classy_classification-1.0.2.dist-info/WHEEL
classy_classification-1.0.2.dist-info/entry_points.txt
classy_classification-1.0.2.dist-info/RECORD
