Metadata-Version: 2.3
Name: classy-classification
Version: 1.0.2
Summary: Have you every struggled with needing a Spacy TextCategorizer but didn't have the time to train one from scratch? Classy Classification is the way to go!
License: MIT
Keywords: spacy,rasa,few-shot classification,nlu,sentence-transformers
Author: David Berenstein
Author-email: david.m.berenstein@gmail.com
Requires-Python: >=3.8,<3.12
Classifier: Development Status :: 4 - Beta
Classifier: Intended Audience :: Developers
Classifier: Intended Audience :: Science/Research
Classifier: License :: OSI Approved :: MIT License
Classifier: Operating System :: OS Independent
Classifier: Programming Language :: Python :: 3
Classifier: Programming Language :: Python :: 3.8
Classifier: Programming Language :: Python :: 3.9
Classifier: Programming Language :: Python :: 3.10
Classifier: Programming Language :: Python :: 3.11
Classifier: Topic :: Scientific/Engineering
Classifier: Topic :: Software Development
Requires-Dist: pandas (>1)
Requires-Dist: scikit-learn (>=1.0,<2.0)
Requires-Dist: sentence-transformers (>2,<4)
Requires-Dist: setuptools (>65.5.0)
Requires-Dist: spacy[transformers] (>=3.0,<4.0)
Requires-Dist: transformers[torch] (>4.20,<5)
Project-URL: Documentation, https://github.com/davidberenstein1957/classy-classification
Project-URL: Homepage, https://github.com/davidberenstein1957/classy-classification
Project-URL: Repository, https://github.com/davidberenstein1957/classy-classification
